mle_training_pack/__init__.py
mle_training_pack/config.py
mle_training_pack/ingest_data.py
mle_training_pack/test.py
mle_training_pack/train.py
mle_training_pack/Tests/test_import.py
mle_training_pack-0.1.2.dist-info/METADATA
mle_training_pack-0.1.2.dist-info/WHEEL
mle_training_pack-0.1.2.dist-info/entry_points.txt
mle_training_pack-0.1.2.dist-info/top_level.txt
mle_training_pack-0.1.2.dist-info/RECORD
