Metadata-Version: 2.1
Name: mle-training-pack
Version: 0.1.2
Summary: Training on python packaging and testing
Home-page: https://github.com/VenkatakrishnanG/mle-training_2
Author: VenkatakrishnanG
Author-email: venkata.govinda@tigeranalytics.com
License: TA
Keywords: MLE Training - Housing
Platform: UNKNOWN
Classifier: Development Status :: 3 - Alpha
Requires-Dist: pandas
Requires-Dist: numpy
Requires-Dist: scipy
Requires-Dist: sklearn
Requires-Dist: logging-tree
Requires-Dist: pytest
Requires-Dist: six
Requires-Dist: argparse
